machine_data_hub/__init__.py
machine_data_hub/cli.py
machine_data_hub-0.1.1.dist-info/entry_points.txt
machine_data_hub-0.1.1.dist-info/LICENSE
machine_data_hub-0.1.1.dist-info/WHEEL
machine_data_hub-0.1.1.dist-info/METADATA
machine_data_hub-0.1.1.dist-info/RECORD
